{
  "navigationBarBackgroundColor": "#E80202",
  "navigationBarTextStyle": "black",
  "navigationBarTitleText": "无界宜选",
  "navigationStyle": "custom",
  "enablePullDownRefresh": true,
  "usingComponents": {
    "tui-icon": "../../../../components/icon/icon",
    "tui-countdown": "../../../components/countdown/countdown",
    "tui-modal1": "../../../components/modal1/modal1",
    "tui-bottom-popup": "../../../components/bottom-popup/bottom-popup",
    "tui-modal": "../../../components/modal/modal",
    "tui-button": "../../../components/button/button",
    "tui-numberbox": "../../../components/numberbox/numberbox"
  }
}